[
  {
   "id": 0,
   "Name": "",
   "Recipes": "",
   "Equipments": "Сироп корицы 20млЛаймовый сок 15млЯблочный сок 35млБелок перепелиного яйца 25млОгурец 75гЛед в кубиках 200гШампанское блюдце1штШейкер1штСтрейнер1штДжиггер1штПресс для цитрусовых1штСоковыжималка1шт"
  },
  {
   "id": 0,
   "Name": "",
   "Recipes": "",
   "Equipments": "Водка Finlandia50млКофейный ликер De Kuyper25млЛед в кубиках 120гРокс1штДжиггер1штКоктейльная ложка1штТрубочки2шт"
  },
  {
   "id": 0,
   "Name": "",
   "Recipes": "",
   "Equipments": "Лондонский сухой джин 40млТрипл сек De Kuyper20млЛимонный сок 20млЛимонная цедра 1штЛед в кубиках 200гБокал сауэр1штШейкер1штСтрейнер1штДжиггер1штПресс для цитрусовых1штНож для цедры1шт"
  }
 ]